aigoofusion/__init__.py
aigoofusion/chat/__init__.py
aigoofusion/chat/aigoo_chat.py
aigoofusion/chat/messages/__init__.py
aigoofusion/chat/messages/message.py
aigoofusion/chat/messages/message_temp.py
aigoofusion/chat/messages/role.py
aigoofusion/chat/messages/tool_call.py
aigoofusion/chat/models/__init__.py
aigoofusion/chat/models/base_ai_model.py
aigoofusion/chat/models/model_formatter.py
aigoofusion/chat/models/model_pricing.py
aigoofusion/chat/models/model_provider.py
aigoofusion/chat/models/bedrock/__init__.py
aigoofusion/chat/models/bedrock/bedrock_config.py
aigoofusion/chat/models/bedrock/bedrock_formatter.py
aigoofusion/chat/models/bedrock/bedrock_model.py
aigoofusion/chat/models/bedrock/bedrock_pricing_list.py
aigoofusion/chat/models/bedrock/bedrock_stream_usage_tracker.py
aigoofusion/chat/models/bedrock/bedrock_usage.py
aigoofusion/chat/models/bedrock/bedrock_usage_tracker.py
aigoofusion/chat/models/openai/__init__.py
aigoofusion/chat/models/openai/openai_config.py
aigoofusion/chat/models/openai/openai_formatter.py
aigoofusion/chat/models/openai/openai_model.py
aigoofusion/chat/models/openai/openai_pricing_list.py
aigoofusion/chat/models/openai/openai_stream_usage_tracker.py
aigoofusion/chat/models/openai/openai_usage.py
aigoofusion/chat/models/openai/openai_usage_tracker.py
aigoofusion/chat/responses/__init__.py
aigoofusion/chat/responses/ai_response.py
aigoofusion/chat/responses/chat_response.py
aigoofusion/chat/tools/__init__.py
aigoofusion/chat/tools/function_parser.py
aigoofusion/chat/tools/function_type_mapping.py
aigoofusion/chat/tools/tool.py
aigoofusion/chat/tools/tool_registry.py
aigoofusion/exception/__init__.py
aigoofusion/exception/aigoo_exception.py
aigoofusion/flow/__init__.py
aigoofusion/flow/aigoo_flow.py
aigoofusion/flow/edge/__init__.py
aigoofusion/flow/edge/edge.py
aigoofusion/flow/helper/__init__.py
aigoofusion/flow/helper/tools_node/__init__.py
aigoofusion/flow/helper/tools_node/tools_node.py
aigoofusion/flow/node/__init__.py
aigoofusion-0.1.11.dist-info/LICENSE
aigoofusion-0.1.11.dist-info/METADATA
aigoofusion-0.1.11.dist-info/WHEEL
aigoofusion-0.1.11.dist-info/top_level.txt
aigoofusion-0.1.11.dist-info/RECORD
