Metadata-Version: 2.1
Name: aigoofusion
Version: 0.1.11
Summary: `AIGooFusion` is a framework for developing applications by large language models (LLMs)
Home-page: https://github.com/irufano/aigoofusion
Author: irufano
Author-email: irufano.official@gmail.com
Classifier: Programming Language :: Python :: 3
Classifier: License :: OSI Approved :: MIT License
Classifier: Operating System :: OS Independent
Requires-Python: >=3.11
License-File: LICENSE
Requires-Dist: pydantic
Provides-Extra: bedrock
Requires-Dist: boto3; extra == "bedrock"
Provides-Extra: openai
Requires-Dist: openai; extra == "openai"
